django_nepkit/__init__.py
django_nepkit/admin.py
django_nepkit/conf.py
django_nepkit/filters.py
django_nepkit/forms.py
django_nepkit/models.py
django_nepkit/serializers.py
django_nepkit/urls.py
django_nepkit/utils.py
django_nepkit/validators.py
django_nepkit/views.py
django_nepkit/widgets.py
django_nepkit/static/django_nepkit/css/admin-nepali-datepicker.css
django_nepkit/static/django_nepkit/js/address-chaining.js
django_nepkit/static/django_nepkit/js/admin-jquery-bridge.js
django_nepkit/static/django_nepkit/js/nepal-data.js
django_nepkit/static/django_nepkit/js/nepali-datepicker-init.js
django_nepkit-0.2.0.dist-info/licenses/LICENSE
example/manage.py
example/demo/__init__.py
example/demo/admin.py
example/demo/apps.py
example/demo/models.py
example/demo/serializers.py
example/demo/tests.py
example/demo/urls.py
example/demo/views.py
example/example_project/__init__.py
example/example_project/settings.py
example/example_project/urls.py
example/example_project/wsgi.py
django_nepkit-0.2.0.dist-info/METADATA
django_nepkit-0.2.0.dist-info/WHEEL
django_nepkit-0.2.0.dist-info/top_level.txt
django_nepkit-0.2.0.dist-info/RECORD
