Metadata-Version: 2.4
Name: django-nepkit
Version: 0.2.0
Summary: Django Nepali date, time, phone, and address fields with helpers.
Home-page: https://github.com/S4NKALP/django-nepkit
Author: Sankalp Tharu
Author-email: Sankalp Tharu <sankalptharu50028@gmail.com>
License: MIT
Project-URL: Homepage, https://github.com/S4NKALP/django-nepkit
Keywords: django,django-fields,django-forms,nepal,nepali,nepali-date,bikram-sambat,nepali-calendar,timezone,asia-kathmandu,phone-number,address,province,district,municipality
Classifier: Framework :: Django
Classifier: Framework :: Django :: 4.2
Classifier: Framework :: Django :: 5.0
Classifier: Framework :: Django :: 5.1
Classifier: Framework :: Django :: 6.0
Classifier: Programming Language :: Python :: 3
Classifier: Programming Language :: Python :: 3.12
Classifier: Programming Language :: Python :: 3.13
Classifier: License :: OSI Approved :: MIT License
Classifier: Intended Audience :: Developers
Classifier: Topic :: Software Development :: Libraries :: Python Modules
Classifier: Topic :: Utilities
Classifier: Operating System :: OS Independent
Classifier: Natural Language :: English
Requires-Python: >=3.11
License-File: LICENSE
Requires-Dist: django>=4.2
Requires-Dist: django-filter>=25.2
Requires-Dist: djangorestframework>=3.16.1
Requires-Dist: nepali>=1.1.3
Provides-Extra: drf
Requires-Dist: djangorestframework>=3.14; extra == "drf"
Requires-Dist: django-filter>=23.1; extra == "drf"
Dynamic: author
Dynamic: home-page
Dynamic: license-file
Dynamic: requires-python
